tortrack/__init__.py
tortrack/__main__.py
tortrack/bot.py
tortrack/cli.py
tortrack/database.py
tortrack/downloader.py
tortrack/handlers.py
tortrack/spotify.py
tortrack/tor_proxy.py
tortrack-1.0.1.dist-info/licenses/LICENSE
tortrack-1.0.1.dist-info/METADATA
tortrack-1.0.1.dist-info/WHEEL
tortrack-1.0.1.dist-info/entry_points.txt
tortrack-1.0.1.dist-info/top_level.txt
tortrack-1.0.1.dist-info/RECORD
