Metadata-Version: 2.4
Name: tortrack
Version: 1.0.1
Summary: Simple Telegram bot for downloading music with Tor anonymity
Home-page: https://github.com/MohammadHNdev/tortrack
Author: Mohammad Hossein Norouzi
Author-email: hosein.norozi434@gmail.com
Project-URL: Bug Reports, https://github.com/MohammadHNdev/tortrack/issues
Project-URL: Source, https://github.com/MohammadHNdev/tortrack
Keywords: telegram bot music download spotify tor anonymous
Classifier: Development Status :: 5 - Production/Stable
Classifier: Intended Audience :: Developers
Classifier: License :: OSI Approved :: MIT License
Classifier: Operating System :: OS Independent
Classifier: Programming Language :: Python :: 3
Classifier: Programming Language :: Python :: 3.8
Classifier: Programming Language :: Python :: 3.9
Classifier: Programming Language :: Python :: 3.10
Classifier: Programming Language :: Python :: 3.11
Classifier: Programming Language :: Python :: 3.12
Classifier: Topic :: Communications :: Chat
Classifier: Topic :: Multimedia :: Sound/Audio
Classifier: Topic :: Internet :: Proxy Servers
Requires-Python: >=3.8
License-File: LICENSE
Requires-Dist: aiogram>=3.0.0
Requires-Dist: spotipy>=2.22.0
Requires-Dist: yt-dlp>=2023.7.6
Requires-Dist: pymongo>=4.0.0
Requires-Dist: motor>=3.0.0
Requires-Dist: python-dotenv>=1.0.0
Requires-Dist: requests>=2.28.0
Requires-Dist: PySocks>=1.7.1
Requires-Dist: stem>=1.8.0
Dynamic: author
Dynamic: author-email
Dynamic: classifier
Dynamic: description
Dynamic: description-content-type
Dynamic: home-page
Dynamic: keywords
Dynamic: license-file
Dynamic: project-url
Dynamic: requires-dist
Dynamic: requires-python
Dynamic: summary
